README.md
setup.py
pygments_yang_lexer.egg-info/PKG-INFO
pygments_yang_lexer.egg-info/SOURCES.txt
pygments_yang_lexer.egg-info/dependency_links.txt
pygments_yang_lexer.egg-info/entry_points.txt
pygments_yang_lexer.egg-info/requires.txt
pygments_yang_lexer.egg-info/top_level.txt
yanglexer/__init__.py
yanglexer/yanglexer.py