Metadata-Version: 1.0
Name: pygments-yang-lexer
Version: 0.2
Summary: A Pygments lexer for YANG modules
Home-page: https://github.com/cmoberg/pygments-yang-lexer
Author: Carl Moberg
Author-email: camoberg@cisco.com
License: New-style BSD
Keywords: yang,pygments,lexer
Platform: UNKNOWN
